README.rst
setup.py
Fabex.egg-info/PKG-INFO
Fabex.egg-info/SOURCES.txt
Fabex.egg-info/dependency_links.txt
Fabex.egg-info/requires.txt
Fabex.egg-info/top_level.txt
fabex/__init__.py
fabex/api.py
fabex/config.py
fabex/context_managers.py
fabex/crypt.py
fabex/decorators.py
fabex/exceptions.py
fabex/fab_api.py
fabex/tasks.py
fabex/contrib/__init__.py
fabex/contrib/files.py
scripts/fxcrypt